{"url":"https://economictimes.indiatimes.com/industry/auto/two-wheelers-three-wheelers/hero-electric-joins-hands-with-readyassist-to-train-20000-mechanics/articleshow/89403129.cms","title":"Hero Electric joins hands with ReadyAssist to train 20,000 mechanics","description":"The company has undertaken the initiative under its Private Garage Owners (PGO) programme. The partnership will aid in identifying mechanics willing to upgrade their skill set and coaching them in the next two years. The training programme will have two stages divided among beginners and experts.","content":"(You can now subscribe to our Economic Times WhatsApp channel)","cleaned_content":"you can now subscribe to our economic times whatsapp channel","timestamp":"2022-02-07T14:48:00+05:30","market_timestamp":"2022-02-07T14:48:00+05:30","off_market_hours":false}