{"url":"https://economictimes.indiatimes.com/industry/auto/two-wheelers-three-wheelers/suzukis-katana-to-launch-in-india-today/articleshow/92652044.cms","title":"Suzuki Motorcycle launches Katana at Rs 13.6 lakh in India","description":"Suzuki Motorcycle India Pvt. Ltd. (SMIPL), the two-wheeler subsidiary of Suzuki Motor Corporation, Japan today launched the KATANA in India. It be available at all the company’s Bike zone dealerships for INR 13,61,000/- (ex-showroom, Delhi) after 04 July 2022.","content":"(You can now subscribe to our Economic Times WhatsApp channel)","cleaned_content":"you can now subscribe to our economic times whatsapp channel","timestamp":"2022-07-04T16:03:00+05:30","market_timestamp":"2022-07-05T09:15:00+05:30","off_market_hours":true}