{"url":"https://economictimes.indiatimes.com/industry/energy/power/adani-firm-raises-offer-for-lanco-amarkantak-power-for-second-time/articleshow/105883822.cms","title":"Adani firm raises offer for Lanco Amarkantak Power for second time","description":"Adani Power had offered Rs 3,650 crore, as reported by ET on November 2. The unsolicited offers are made almost 10-11 months after 95% of lenders voted for a plan by the Power Finance Corp (PFC) led consortium.","content":"(You can now subscribe to our Economic Times WhatsApp channel)","cleaned_content":"you can now subscribe to our economic times whatsapp channel","timestamp":"2023-12-13T17:41:00+05:30","market_timestamp":"2023-12-14T09:15:00+05:30","off_market_hours":true}