{"url":"https://economictimes.indiatimes.com/industry/auto/two-wheelers-three-wheelers/hero-motocorp-launches-xtreme-125r-at-rs-95000-price-mileage-speed-and-other-features/articleshow/107075275.cms","title":"Hero Motocorp launches Xtreme 125R at Rs 95,000: Price, mileage, speed and other features","description":"A 125cc, single-cylinder, air-cooled engine powers the new bike. It can produce out 11.5 bhp and 10.5Nm and comes mated to a five-speed gearbox.","content":"(You can now subscribe to our Economic Times WhatsApp channel)","cleaned_content":"you can now subscribe to our economic times whatsapp channel","timestamp":"2024-01-23T12:57:00+05:30","market_timestamp":"2024-01-23T12:57:00+05:30","off_market_hours":false}