{"url":"https://economictimes.indiatimes.com/industry/energy/power/govt-industry-gear-up-for-india-energy-week-in-goa-to-showcase-business-opportunities/articleshow/107240272.cms","title":"Govt, industry gear up for India Energy Week in Goa; to showcase business opportunities","description":"The first edition of IEW was held in Bengaluru last year. In the second edition to be held in Goa, 900 exhibitors will participate, about 30% more than last year. The total number of participants is expected to be over 35,000 at IEW. Goa would also have dedicated country pavilions of Canada, Germany, Netherlands, Russia, the UK, and the US.","content":"(You can now subscribe to our Economic Times WhatsApp channel)","cleaned_content":"you can now subscribe to our economic times whatsapp channel","timestamp":"2024-01-29T23:48:00+05:30","market_timestamp":"2024-01-30T09:15:00+05:30","off_market_hours":true}