{"url":"https://economictimes.indiatimes.com/industry/services/hotels-/-restaurants/hospitality-travel-sector-players-want-infrastructure-status-for-hotel-industry/articleshow/106902611.cms","title":"Budget 2024 wishlist: What hospitality and travel sector players want from the Modi government","description":"Interim Budget 2024: Hospitality and travel sector players demand infrastructure status for the hotel industry, tax exemption on LTA, and reduction in income tax levels. They also recommend removal of TDS on automated bookings and reducing the number of licenses required to establish a hotel. The industry seeks rationalization of GST and a Central single window clearance for hotel projects. Lowering of GST rates on hotel room tariffs above Rs 7,500 is also requested.","content":"(You can now subscribe to our Economic Times WhatsApp channel)","cleaned_content":"you can now subscribe to our economic times whatsapp channel","timestamp":"2024-02-01T09:57:00+05:30","market_timestamp":"2024-02-01T09:57:00+05:30","off_market_hours":false}