{"url":"https://economictimes.indiatimes.com/industry/banking/finance/indias-makemytrip-policybazaar-warn-rbi-of-fintech-hit-after-paytm-crackdown-letter/articleshow/107465856.cms","title":"India's MakeMyTrip, PolicyBazaar warn RBI of fintech hit after Paytm crackdown: Letter","description":"India's MakeMyTrip and PolicyBazaar have expressed concerns to the central bank about the impact of its crackdown on Paytm, a digital payments firm. They argue that the decision could harm investment in the fast-growing financial-technology sector, discourage innovation, and send a negative signal to the global business community.","content":"(You can now subscribe to our Economic Times WhatsApp channel)","cleaned_content":"you can now subscribe to our economic times whatsapp channel","timestamp":"2024-02-06T20:29:00+05:30","market_timestamp":"2024-02-07T09:15:00+05:30","off_market_hours":true}