{"url":"https://economictimes.indiatimes.com/industry/services/hotels-/-restaurants/radisson-hotel-group-announces-second-hotel-in-ayodhya-with-easemytrip-jeewani-hospitality/articleshow/107845332.cms","title":"Radisson Hotel Group announces second hotel in Ayodhya with EaseMyTrip, Jeewani Hospitality","description":"Radisson Hotel Group announces the opening of its second hotel in Ayodhya, developed by Jeewani Hospitality. The hotel is expected to open in 2027. The hotel will be located near Maharishi Valmiki International Airport and will offer road connectivity via National Highway-27. Guests can explore nearby religious sites and the partnership with EaseMyTrip is highly regarded.","content":"(You can now subscribe to our Economic Times WhatsApp channel)","cleaned_content":"you can now subscribe to our economic times whatsapp channel","timestamp":"2024-02-20T13:51:00+05:30","market_timestamp":"2024-02-20T13:51:00+05:30","off_market_hours":false}