{"url":"https://economictimes.indiatimes.com/industry/services/hotels-/-restaurants/industry-occupancy-to-be-at-decadal-highs-in-fy25-arrs-to-inch-towards-fy28-peak-this-fiscal/articleshow/107845304.cms","title":"Industry occupancy to be at decadal highs in FY25, ARRs to inch towards FY28 peak this fiscal","description":"The hospitality industry is poised for robust growth in fiscal year 2025, with occupancy rates expected to reach highs not seen in a decade. Average room rates are also projected to approach peak levels from fiscal year 2008. Factors driving this growth include strong demand for leisure travel, brand preferences, corporate MICE demand, and religious tourism. The outlook remains positive in the medium term, supported by infrastructure development, India's economic progress, and evolving consumer preferences favoring experiential travel.","content":"(You can now subscribe to our Economic Times WhatsApp channel)","cleaned_content":"you can now subscribe to our economic times whatsapp channel","timestamp":"2024-02-20T16:28:00+05:30","market_timestamp":"2024-02-21T09:15:00+05:30","off_market_hours":true}