{"url":"https://economictimes.indiatimes.com/industry/banking/finance/banking/banks-ask-rbi-to-ease-liquidity-rule-to-keep-credit-taps-open/articleshow/110853738.cms","title":"Banks ask RBI to ease liquidity rule to keep credit taps open","description":"Indian banks are urging the industry regulator to relax the current liquidity coverage requirements. They believe easing these mandates will free up more funds for lending.","content":"(You can now subscribe to our Economic Times WhatsApp channel)","cleaned_content":"you can now subscribe to our economic times whatsapp channel","timestamp":"2024-06-10T00:46:00+05:30","market_timestamp":"2024-06-10T09:15:00+05:30","off_market_hours":true}