{"url":"https://economictimes.indiatimes.com/industry/energy/power/bhel-bags-rs-13300-cr-order-to-set-up-1600-mw-thermal-power-project/articleshow/111320992.cms","title":"BHEL bags Rs 13,300 cr order to set up 1600 MW-thermal power project","description":"Commensurate with the goal of the central government to ensure the energy security of the country, DVC has finalised the tender for the engineering, procurement and construction (EPC) package of Koderma TPS (2X800MW) in Jharkhand, with Bharat Heavy Electricals Ltd (BHEL) for Rs 13,300 Crore on June 26, 2024, a power ministry statement said.","content":"(You can now subscribe to our Economic Times WhatsApp channel)","cleaned_content":"you can now subscribe to our economic times whatsapp channel","timestamp":"2024-06-27T21:41:00+05:30","market_timestamp":"2024-06-28T09:15:00+05:30","off_market_hours":true}