{"url":"https://economictimes.indiatimes.com/industry/renewables/budget-2024-more-fame-less-gst-what-the-ev-industry-wants-from-fm-sitharaman/articleshow/111598424.cms","title":"Budget 2024: 'More FAME, Less GST' - What the EV industry wants from FM Sitharaman","description":"Industry players are looking forward to potential GST concessions and incentives for electric vehicles in the upcoming Budget FY25. Expectations include policies like FAME 3.0 to enhance the EV ecosystem, promote R\u0026D, and support local manufacturing for sustainable transportation in India.","content":"(You can now subscribe to our Economic Times WhatsApp channel)","cleaned_content":"you can now subscribe to our economic times whatsapp channel","timestamp":"2024-07-11T14:03:00+05:30","market_timestamp":"2024-07-11T14:03:00+05:30","off_market_hours":false}