{"url":"https://economictimes.indiatimes.com/industry/banking/finance/banking/equitas-small-finance-bank-clocks-35-deposits-growth-against-sectoral-trend/articleshow/111492129.cms","title":"Equitas Small Finance Bank clocks 35% deposits growth, bucks sectoral trend","description":"Equitas Small Finance Bank, with a priority sector focus, achieved a 35.4% year-on-year deposit growth to Rs 37524 crore by the end of June, surpassing the sectoral average of 12%. Advances increased 17.8% to Rs 34872 crore, although the CASA ratio fell to 31% due to faster term deposits growth. Provisional figures submitted to stock exchanges confirmed these results.","content":"(You can now subscribe to our Economic Times WhatsApp channel)","cleaned_content":"you can now subscribe to our economic times whatsapp channel","timestamp":"2024-07-04T19:08:00+05:30","market_timestamp":"2024-07-05T09:15:00+05:30","off_market_hours":true}