{"url":"https://economictimes.indiatimes.com/industry/banking/finance/banking/incremental-credit-slows-down-until-mid-june/articleshow/111557081.cms","title":"Incremental credit slows down until mid-June","description":"Incremental loans increased Rs 2.79 lakh crore or 1.7 % this fiscal year up to June 14 compared to Rs 3.48 lakh crore or 2.5 percent a year ago reflecting a slowdown in credit demand for investments as well as working capital needs- and indicator of level of economic activity.","content":"(You can now subscribe to our Economic Times WhatsApp channel)","cleaned_content":"you can now subscribe to our economic times whatsapp channel","timestamp":"2024-07-07T18:39:00+05:30","market_timestamp":"2024-07-08T09:15:00+05:30","off_market_hours":true}