{"url":"https://economictimes.indiatimes.com/industry/banking/finance/banking/jio-financial-services-gets-rbi-nod-to-become-core-investment-company/articleshow/111674307.cms","title":"Jio Financial Services gets RBI nod to become core investment company","description":"The Reserve Bank of India on Thursday evening approved Jio Financial's conversion from a Non-Banking Financial Company (NBFC) to a Core Investment Company (CIC), the company said in a filing.","content":"(You can now subscribe to our Economic Times WhatsApp channel)","cleaned_content":"you can now subscribe to our economic times whatsapp channel","timestamp":"2024-07-12T10:16:00+05:30","market_timestamp":"2024-07-12T10:16:00+05:30","off_market_hours":false}