{"url":"https://economictimes.indiatimes.com/industry/banking/finance/banking/goldman-sachs-appoints-sudarshan-ramakrishnan-and-devarajan-nambakam-as-the-co-heads-of-investment-banking-in-india/articleshow/111749673.cms","title":"Goldman Sachs appoints Sudarshan Ramakrishnan and Devarajan Nambakam as the co-heads of Investment Banking in India","description":"Goldman Sachs has named Sudarshan Ramakrishnan and Devarajan Nambakam as co-heads of its investment banking business in India. Sunil Khaitan has also joined as managing director. Ramakrishnan and Nambakam will drive growth strategy, reporting to Sonjoy Chatterjee. The firm aims to leverage global expertise to deepen client relationships amidst India's economic growth.","content":"(You can now subscribe to our Economic Times WhatsApp channel)","cleaned_content":"you can now subscribe to our economic times whatsapp channel","timestamp":"2024-07-15T13:44:00+05:30","market_timestamp":"2024-07-15T13:44:00+05:30","off_market_hours":false}