{"url":"https://economictimes.indiatimes.com/industry/energy/power/coal-based-power-capacity-needs-investment-of-rs-6-67-lakh-cr-to-meet-demand-by-2032-power-ministry/articleshow/112018307.cms","title":"Coal based power capacity needs investment of Rs 6.67 lakh cr to meet demand by 2032: Power Ministry","description":"The Power Ministry has announced a plan requiring a Rs 6.67 lakh crore investment to reach the estimated electricity demand by 2031-32. The Central Electricity Authority determined that the country needs a coal \u0026 lignite installed capacity of 283 GW. The country  currently produces 217.5 GW. The Government of India aims to add at least 80 GW of coal-based capacity by 2031-32, alongside a push for non-fossil fuel-based electricity generation to reach a target of 50 per cent by 2030. Currently the figure stands at 45.5 per cent.","content":"(You can now subscribe to our Economic Times WhatsApp channel)","cleaned_content":"you can now subscribe to our economic times whatsapp channel","timestamp":"2024-07-25T18:02:00+05:30","market_timestamp":"2024-07-26T09:15:00+05:30","off_market_hours":true}