{"url":"https://economictimes.indiatimes.com/industry/renewables/softbank-backed-ola-electric-suspends-car-project-to-focus-on-scooters-bikes/articleshow/112030716.cms","title":"SoftBank-backed Ola Electric suspends car project to focus on scooters, bikes","description":"Ola founder Bhavish Aggarwal reiterated those plans as recently as Sept. 2023 in an interview with Forbes, but the two sources said the project is now suspended ahead of its planned August IPO, where it is set to raise around $660 million.","content":"(You can now subscribe to our Economic Times WhatsApp channel)","cleaned_content":"you can now subscribe to our economic times whatsapp channel","timestamp":"2024-07-25T17:30:00+05:30","market_timestamp":"2024-07-26T09:15:00+05:30","off_market_hours":true}