{"url":"https://economictimes.indiatimes.com/industry/banking/finance/credit-line-on-upi-could-cross-1-trillion-in-transaction-value-by-2030-zeta/articleshow/112709504.cms","title":"Credit line on UPI could cross $1 trillion in transaction value by 2030: Zeta","description":"The credit line on UPI could exceed $1 trillion in transaction value by 2030, according to Zeta. Key drivers include rising credit demand, a shift towards digital payments, and improved credit discovery and utilization. UPI credit lines provide banks with alternative data for better credit assessments, especially in under-served regions.","content":"(You can now subscribe to our Economic Times WhatsApp channel)","cleaned_content":"you can now subscribe to our economic times whatsapp channel","timestamp":"2024-08-22T15:42:00+05:30","market_timestamp":"2024-08-23T09:15:00+05:30","off_market_hours":true}