{"url":"https://economictimes.indiatimes.com/industry/energy/power/adani-incorporates-new-power-company-in-uae-will-invest-in-power-infra-related-fields/articleshow/112825079.cms","title":"Adani incorporates new power company in UAE, will invest in power, infra \u0026 related fields","description":"Adani Power has incorporated a new subsidiary, Adani Power Middle East Ltd, in Abu Dhabi to invest in power and infrastructure sectors. The new subsidiary, entirely owned by Adani Power, has an authorized capital of USD 27,000. Adani Power continues expanding its power projects, recently signing a significant contract with BHEL for supercritical thermal power projects.","content":"(You can now subscribe to our Economic Times WhatsApp channel)","cleaned_content":"you can now subscribe to our economic times whatsapp channel","timestamp":"2024-08-27T10:35:00+05:30","market_timestamp":"2024-08-27T10:35:00+05:30","off_market_hours":false}