{"url":"https://economictimes.indiatimes.com/industry/renewables/govts-20-ethanol-blending-goal-in-esy-2025-will-need-more-sugarcane-report/articleshow/112631931.cms","title":"Govt's 20% ethanol blending goal in ESY 2025 will need more sugarcane: Report","description":"By 2025, the government aims to blend 20 percent ethanol in petrol, which will necessitate higher sugarcane utilization, thereby improving sugar inventory and millers' cash flows. While grain-based ethanol production is set to increase, the reduction in sugarcane output due to erratic rainfall is expected to impact supply, targeting 14 percent blending in 2024.","content":"(You can now subscribe to our Economic Times WhatsApp channel)","cleaned_content":"you can now subscribe to our economic times whatsapp channel","timestamp":"2024-08-19T19:49:00+05:30","market_timestamp":"2024-08-20T09:15:00+05:30","off_market_hours":true}