{"url":"https://economictimes.indiatimes.com/industry/banking/finance/small-ticket-business-loans-driving-shriram-finances-msme-growth/articleshow/112621477.cms","title":"Small ticket business loans driving Shriram Finance's MSME growth","description":"Shriram Finance Ltd anticipated sustained growth in its micro and small enterprises sector, driven by demand for small loans. The company expected a yearly 25% growth in the MSME portfolio. In contrast, the commercial vehicle business saw slower growth. Shriram has diversified its operations and projects a notable rise in MSME loans soon.","content":"(You can now subscribe to our Economic Times WhatsApp channel)","cleaned_content":"you can now subscribe to our economic times whatsapp channel","timestamp":"2024-08-19T11:39:00+05:30","market_timestamp":"2024-08-19T11:39:00+05:30","off_market_hours":false}