{"url":"https://economictimes.indiatimes.com/industry/banking/finance/banking/yes-banks-stake-saleruns-into-rbi-hurdle/articleshow/113302393.cms","title":"Yes Bank's stake sale runs into RBI hurdle","description":"In March 2020, a State Bank of India-led consortium bailed out Yes Bank by infusing Rs 10,000 crore-a move primarily aimed at protecting depositors. SBI, which acquired a 49% stake with a three-year lock-in, now holds 24% after Yes Bank raised money through a follow-on public issue and the preferential issue of shares to private equity investors Carlyle and Advent International.","content":"(You can now subscribe to our Economic Times WhatsApp channel)","cleaned_content":"you can now subscribe to our economic times whatsapp channel","timestamp":"2024-09-13T00:32:00+05:30","market_timestamp":"2024-09-13T09:15:00+05:30","off_market_hours":true}