{"url":"https://economictimes.indiatimes.com/industry/services/hotels-/-restaurants/indians-travel-far-and-wide-to-reach-concert-paradise/articleshow/113825940.cms","title":"Indians travel far and wide to reach concert paradise","description":"Rooms are available at The Fern Residency Turbhe but for a hefty price of Rs 236,943 (including taxes) for two nights for the dates. Four Points by Sheraton Navi Mumbai will set you back by Rs 135,700 (including taxes) on January 21, the third concert date. The craze is not limited to Coldplay alone. Indians' love for music is triggering a surge in bookings for top musical acts with travel industry insiders reporting a three-to-fivefold jump in online searches for concert-linked experiential trips in India and overseas. Thomas Cook India recently arranged a father-daughter 'music concert bonding' trip in Los Angeles for Rs 14 lakh.","content":"(You can now subscribe to our Economic Times WhatsApp channel)","cleaned_content":"you can now subscribe to our economic times whatsapp channel","timestamp":"2024-10-01T09:24:00+05:30","market_timestamp":"2024-10-01T09:24:00+05:30","off_market_hours":false}