{"url":"https://economictimes.indiatimes.com/industry/renewables/govt-launches-pm-e-drive-subsidy-scheme-with-rs-10900-cr-outlay/articleshow/113852329.cms","title":"Govt launches PM E-DRIVE subsidy scheme with Rs 10,900 cr outlay","description":"The government has introduced the PM E-DRIVE Scheme to encourage electric vehicles' adoption and infrastructure development. The scheme will run from October 1, 2024, to March 31, 2026. Subsidies will be provided for various EVs and the installation of public charging stations. Incentives will also support EV testing facilities and the deployment of e-trucks.","content":"(You can now subscribe to our Economic Times WhatsApp channel)","cleaned_content":"you can now subscribe to our economic times whatsapp channel","timestamp":"2024-10-01T17:34:00+05:30","market_timestamp":"2024-10-03T09:15:00+05:30","off_market_hours":true}