{"url":"https://economictimes.indiatimes.com/industry/renewables/ireda-gets-dipam-nod-to-set-up-subsidiary-to-handle-retail-b2b-biz-in-re-segment/articleshow/114144877.cms","title":"IREDA gets DIPAM nod to set up subsidiary to handle retail, B2B biz in RE segment","description":"IREDA, a state-run RE financing agency, has received DIPAM’s approval to form a subsidiary for handling retail and B2B business in renewable energy. The new unit will focus on PM-Suryaghar, PM-KUSUM schemes, EVs, energy storage, and sustainability, enhancing support for urban and rural consumers.","content":"(You can now subscribe to our Economic Times WhatsApp channel)","cleaned_content":"you can now subscribe to our economic times whatsapp channel","timestamp":"2024-10-11T14:33:00+05:30","market_timestamp":"2024-10-11T14:33:00+05:30","off_market_hours":false}