{"url":"https://economictimes.indiatimes.com/industry/auto/two-wheelers-three-wheelers/hero-electric-takes-hero-moto-to-court-over-use-of-brand-name-in-ev-space/articleshow/88703892.cms","title":"Hero Electric drags Hero Moto to court over use of brand name in EV space","description":"Vijay Munjal and son Naveen Munjal, owners of Hero Electric, have taken cousin Pawan Munjal, CMD of two-wheeler market leader Hero MotoCorp, to court for the use of the Hero brand name for Hero MotoCorp's soon-to-debut EV range.","content":"(You can now subscribe to our Economic Times WhatsApp channel)","cleaned_content":"you can now subscribe to our economic times whatsapp channel","timestamp":"2022-01-06T09:46:00+05:30","market_timestamp":"2022-01-06T09:46:00+05:30","off_market_hours":false}