{"url":"https://economictimes.indiatimes.com/industry/auto/two-wheelers-three-wheelers/hero-motocorp-bets-on-harley-partnership-record-product-launches-to-strengthen-premium-segment/articleshow/101465626.cms","title":"Hero MotoCorp bets on Harley partnership, record product launches to strengthen premium segment","description":"Hero MotoCorp Executive Chairman Pawan Munjal said the company is in the process of introducing a record number of new products in the premium segment (150cc-450cc) over the next two years to get to its \"rightful place\" in the vertical.","content":"(You can now subscribe to our Economic Times WhatsApp channel)","cleaned_content":"you can now subscribe to our economic times whatsapp channel","timestamp":"2023-07-04T10:29:00+05:30","market_timestamp":"2023-07-04T10:29:00+05:30","off_market_hours":false}