{"url":"https://economictimes.indiatimes.com/industry/services/hotels-/-restaurants/postcard-will-launch-indias-most-expensive-hotel-ceo-kapil-chopra/articleshow/104294174.cms","title":"Postcard will launch India's most expensive hotel: CEO Kapil Chopra","description":"\"We are profitable at a company level. We have institutional funds working with us. I think we are building the next level of global hospitality out of India,\" said Chopra. Last year, on a conservative basis, it had ₹1,563 crore of hotel assets under management, said Kapil Chopra.","content":"(You can now subscribe to our Economic Times WhatsApp channel)","cleaned_content":"you can now subscribe to our economic times whatsapp channel","timestamp":"2023-10-10T02:51:00+05:30","market_timestamp":"2023-10-10T09:15:00+05:30","off_market_hours":true}