{"url":"https://economictimes.indiatimes.com/industry/auto/auto-news/sunroof-surge-indias-buyers-drive-demand-prompting-carmakers-to-elevate-the-roof-game/articleshow/107039058.cms","title":"Sunroof Surge: India's buyers drive demand, prompting carmakers to elevate the roof game","description":"Once considered a luxury feature, currently more than one out of every four cars sold in the local market is equipped with a sunroof, up from just about 7% five years ago. In models where the feature is available, sales are even higher at 55%. Be it premium hatchbacks, sedans or fast-moving sport-utility vehicles, demand for sunroofs is on the rise in a predominantly tropical country.","content":"(You can now subscribe to our Economic Times WhatsApp channel)","cleaned_content":"you can now subscribe to our economic times whatsapp channel","timestamp":"2024-01-22T07:48:00+05:30","market_timestamp":"2024-01-22T09:15:00+05:30","off_market_hours":true}