{"url":"https://economictimes.indiatimes.com/industry/banking/finance/satin-creditcare-network-reports-33-yoy-jump-in-march-quarter/articleshow/109693498.cms","title":"Satin CreditCare Network reports 33% YoY jump in March quarter","description":"Satin CreditCare Network's net profit rose 33% to Rs 125 crore in March quarter, driven by robust growth. Assets under management increased by 34% in FY24. The company achieved its highest-ever net profit for the year.","content":"(You can now subscribe to our Economic Times WhatsApp channel)","cleaned_content":"you can now subscribe to our economic times whatsapp channel","timestamp":"2024-04-29T16:43:00+05:30","market_timestamp":"2024-04-30T09:15:00+05:30","off_market_hours":true}