{"url":"https://economictimes.indiatimes.com/industry/energy/power/26-companies-queue-up-for-ksk-mahanadi-power-project/articleshow/109738171.cms","title":"26 companies queue up for KSK Mahanadi power project","description":"The National Company Law Tribunal (NCLT) vacated the stay on the auction of the power project on April 5, paving the way for a fresh round of bidding. The total claim of lenders on the project is pegged at about Rs 32,000 crore. These companies have given 'expressions of interest', which were to be submitted by April 26 and the timeline to give a resolution plan by the interested parties is June 18, according to the timeline set by resolution professional Sumit Binani.","content":"(You can now subscribe to our Economic Times WhatsApp channel)","cleaned_content":"you can now subscribe to our economic times whatsapp channel","timestamp":"2024-05-01T01:02:00+05:30","market_timestamp":"2024-05-01T09:15:00+05:30","off_market_hours":true}