{"url":"https://economictimes.indiatimes.com/industry/banking/finance/reliance-capital-administrator-seeks-10-days-extension-from-rbi-to-transfer-assets-to-hinduja-group/articleshow/110214890.cms","title":"Reliance Capital Administrator seeks 10 days extension from RBI to transfer assets to Hinduja Group","description":"The National Company Law Tribunal (NCLT) Mumbai, while approving the resolution plan on February 27, directed IndusInd International Holdings Ltd to implement it within 90 days ending May 27.","content":"(You can now subscribe to our Economic Times WhatsApp channel)","cleaned_content":"you can now subscribe to our economic times whatsapp channel","timestamp":"2024-05-17T21:19:00+05:30","market_timestamp":"2024-05-20T09:15:00+05:30","off_market_hours":true}