{"url":"https://economictimes.indiatimes.com/industry/banking/finance/credit-card-base-reaches-103-million-spending-hits-rs-1-65-trillion/articleshow/111292536.cms","title":"Credit Card issuance soars despite worries over unsecured loans","description":"Credit card base in India grew 18% YoY to reach 103 million, with HDFC bank adding the most new cards. However, Kotak Mahindra bank saw a sharp drop amid RBI restrictions. Card spending also grew 17% YoY to reach Rs 1.65 trillion. The credit card industry has seen a continuous decline due to caution about large unsecured loans and asset quality issues.","content":"(You can now subscribe to our Economic Times WhatsApp channel)","cleaned_content":"you can now subscribe to our economic times whatsapp channel","timestamp":"2024-06-27T00:40:00+05:30","market_timestamp":"2024-06-27T09:15:00+05:30","off_market_hours":true}