{"url":"https://economictimes.indiatimes.com/industry/renewables/changes-likely-in-indias-new-ev-policy-may-benefit-legacy-car-companies/articleshow/111560035.cms","title":"Changes likely in India's new EV policy, may benefit legacy car companies","description":"The move comes as US electric carmaker Tesla Inc is still to make any firm commitment on building a factory in India. The policy, which aims to accelerate the local manufacturing of high-end electric cars, currently supports only fresh investments. Consultations are also on with stakeholders on another key issue troubling carmakers.","content":"(You can now subscribe to our Economic Times WhatsApp channel)","cleaned_content":"you can now subscribe to our economic times whatsapp channel","timestamp":"2024-07-08T05:30:00+05:30","market_timestamp":"2024-07-08T09:15:00+05:30","off_market_hours":true}