{"url":"https://economictimes.indiatimes.com/industry/auto/auto-news/current-gst-rate-for-pvs-outdated-needs-a-relook-jsw-mg-motor-india-ceo-emeritus/articleshow/111810551.cms","title":"Current GST rate for PVs outdated; needs a relook: JSW MG Motor India CEO Emeritus","description":"Amid speculations that hybrid vehicles could be considered for tax incentives ahead of the Union Budget, he said only the strong 'plug-in' hybrids, which have the capability to also run as a battery electric vehicle independent from the internal combustion engine, should be considered for such benefits.","content":"(You can now subscribe to our Economic Times WhatsApp channel)","cleaned_content":"you can now subscribe to our economic times whatsapp channel","timestamp":"2024-07-17T17:14:00+05:30","market_timestamp":"2024-07-18T09:15:00+05:30","off_market_hours":true}