{"url":"https://economictimes.indiatimes.com/industry/auto/auto-news/japans-suzuki-aims-to-cut-vehicle-weight-of-key-model-by-15-over-a-decade/articleshow/111799073.cms","title":"Suzuki outlines tech strategy for next 10 years for various markets including India","description":"The automaker, which has around 58 per cent stake in the country's largest carmaker maruti Suzuki India, said it will further evolve the light-weight and safety body 'HEARTECT', and also work to minimise energy consumption through weight reduction technology.","content":"(You can now subscribe to our Economic Times WhatsApp channel)","cleaned_content":"you can now subscribe to our economic times whatsapp channel","timestamp":"2024-07-17T10:34:00+05:30","market_timestamp":"2024-07-17T10:34:00+05:30","off_market_hours":false}