{"url":"https://economictimes.indiatimes.com/industry/energy/power/detailed-project-reports-of-two-hydro-pumped-storage-plants-approved-in-record-time-power-ministry/articleshow/112222793.cms","title":"Detailed project reports of two hydro pumped storage plants approved in record time: Power ministry","description":"The Central Electricity Authority (CEA) has approved the detailed project report of two hydro pumped storage plants in India, the 600 MW Upper Indravati in Odisha and the 2,000 MW Sharavathy in Karnataka. The CEA revised guidelines to simplify the process for preparing detailed project reports (DPRs) of PSPs and their concurrence. The ministry said the government prioritizes the development of energy storage systems, particularly PSPs, to ensure energy security.","content":"(You can now subscribe to our Economic Times WhatsApp channel)","cleaned_content":"you can now subscribe to our economic times whatsapp channel","timestamp":"2024-08-02T15:55:00+05:30","market_timestamp":"2024-08-05T09:15:00+05:30","off_market_hours":true}