{"url":"https://economictimes.indiatimes.com/industry/renewables/ford-eyeing-a-comeback-us-car-giant-may-re-enter-india-with-a-green-twist/articleshow/112237617.cms","title":"Ford eyeing a comeback? US car giant may re-enter India with a green twist","description":"Ford Comback in India: Ford is exploring a re-entry into the Indian market, focusing on electrics and sustainability. After exiting India in 2021, Ford is evaluating a feasibility report on new investments and production for local sales and exports. The company, which had invested over $2 billion in India, sees the market as vital for future growth amidst stagnation in Western markets.","content":"(You can now subscribe to our Economic Times WhatsApp channel)","cleaned_content":"you can now subscribe to our economic times whatsapp channel","timestamp":"2024-08-04T00:18:00+05:30","market_timestamp":"2024-08-05T09:15:00+05:30","off_market_hours":true}