{"url":"https://economictimes.indiatimes.com/industry/banking/finance/banking/nclat-reserves-order-on-sbi-plea-for-funds-from-ilfs-co/articleshow/112384336.cms","title":"NCLAT reserves order on SBI plea for funds from IL\u0026FS Co","description":"The NCLAT reserved its decision on SBI's plea for an interim distribution of Rs 275 crore from the escrow account of Baleshwar Kharagpur Expressway Ltd. In April, NCLAT had ruled that secured creditors like SBI should be paid before other creditors. SBI emphasized the long wait of almost six years for fund distribution.","content":"(You can now subscribe to our Economic Times WhatsApp channel)","cleaned_content":"you can now subscribe to our economic times whatsapp channel","timestamp":"2024-08-08T23:53:00+05:30","market_timestamp":"2024-08-09T09:15:00+05:30","off_market_hours":true}