{"url":"https://economictimes.indiatimes.com/industry/auto/auto-news/maruti-agm-auto-industry-icon-rc-bhargava-debunks-an-enduring-myth-citing-examples-from-india-story/articleshow/112828122.cms","title":"Maruti AGM: Auto industry icon RC Bhargava debunks an enduring myth citing examples from India story","description":"In Maruti Suzuki India’s Annual General Meeting, Chairman RC Bhargava highlighted India's achievement in combining rapid economic growth and a democratic political system. He praised the government's consistent policies, which he said bolster industry confidence in sustained growth. The auto industry icon also emphasised that democratic processes are key to creating a more equitable society.","content":"(You can now subscribe to our Economic Times WhatsApp channel)","cleaned_content":"you can now subscribe to our economic times whatsapp channel","timestamp":"2024-08-27T12:09:00+05:30","market_timestamp":"2024-08-27T12:09:00+05:30","off_market_hours":false}