{"url":"https://economictimes.indiatimes.com/industry/renewables/indias-green-hydrogen-push-what-the-government-must-focus-on-following-the-union-budget/articleshow/112648804.cms","title":"India’s Green Hydrogen Push: What the government must focus on following the Union Budget","description":"The 2024 Union Budget of India designated INR 600 crore to the National Green Hydrogen Mission, aiming to enhance green hydrogen production. Key focuses include demand creation, de-risking finance, and equitable resource use. The Mission aspires to reach a production capacity of 5 million metric tonnes per year by 2030, with significant incentives for domestic electrolyzer manufacturing.","content":"(You can now subscribe to our Economic Times WhatsApp channel)","cleaned_content":"you can now subscribe to our economic times whatsapp channel","timestamp":"2024-08-22T14:19:00+05:30","market_timestamp":"2024-08-22T14:19:00+05:30","off_market_hours":false}