{"url":"https://economictimes.indiatimes.com/industry/renewables/govt-approves-rs-12461-cr-support-for-31350-mw-hydro-power-projects/articleshow/113268521.cms","title":"Govt approves Rs 12,461 cr support for 31,350 MW hydro power projects","description":"The Union Cabinet has approved a Rs 12,461 crore outlay to support the development of 31,350 MW hydropower projects over the next eight years. The scheme, applicable to projects above 25 MW capacity, aims to improve infrastructure and promote investment in the hydro power sector.","content":"(You can now subscribe to our Economic Times WhatsApp channel)","cleaned_content":"you can now subscribe to our economic times whatsapp channel","timestamp":"2024-09-11T22:34:00+05:30","market_timestamp":"2024-09-12T09:15:00+05:30","off_market_hours":true}