{"url":"https://economictimes.indiatimes.com/industry/banking/finance/banking/after-nclats-nod-idfc-idfc-first-bank-merger-to-be-effective-october-1/articleshow/113745090.cms","title":"After NCLT's nod, IDFC-IDFC First Bank merger to be effective October 1","description":"The National Company Law Tribunal has approved the merger of IDFC FHCL with IDFC Limited, effective September 30, and the subsequent merger of IDFC Limited with IDFC FIRST Bank from October 1. The Reserve Bank of India had already given its nod for this reverse merger in December 2023.","content":"(You can now subscribe to our Economic Times WhatsApp channel)","cleaned_content":"you can now subscribe to our economic times whatsapp channel","timestamp":"2024-09-28T03:35:00+05:30","market_timestamp":"2024-09-30T09:15:00+05:30","off_market_hours":true}