{"url":"https://economictimes.indiatimes.com/industry/renewables/tesla-plans-four-new-batteries-in-2026-including-for-robotaxi-the-information-reports/articleshow/113914935.cms","title":"Tesla plans four new batteries in 2026, including for robotaxi, The Information reports","description":"Tesla is designing four new versions of its in-house 4680 battery to power future models like the Cybertruck and a robotaxi. The company faces production challenges with cathode losses and dry-coated cells but aims to ramp up production by 2026 to improve margins and efficiency.","content":"(You can now subscribe to our Economic Times WhatsApp channel)","cleaned_content":"you can now subscribe to our economic times whatsapp channel","timestamp":"2024-10-03T21:22:00+05:30","market_timestamp":"2024-10-04T09:15:00+05:30","off_market_hours":true}